WebStarterKit/__init__.py
WebStarterKit/cli.py
WebStarterKit/create_project.py
webstarterkit-0.1.1.dist-info/METADATA
webstarterkit-0.1.1.dist-info/WHEEL
webstarterkit-0.1.1.dist-info/entry_points.txt
webstarterkit-0.1.1.dist-info/top_level.txt
webstarterkit-0.1.1.dist-info/RECORD
