Metadata-Version: 2.2
Name: WebStarterKit
Version: 0.1.1
Summary: A CLI tool to generate a basic HTML, CSS, and JS project structure.
Home-page: https://github.com/shubham-parida01/WebStarterKit
Author: Shubham Parida
Author-email: paridashub9871@gmail.com
License: MIT
Classifier: Programming Language :: Python :: 3
Classifier: License :: OSI Approved :: MIT License
Classifier: Operating System :: OS Independent
Requires-Python: >=3.6
Dynamic: author
Dynamic: author-email
Dynamic: classifier
Dynamic: description
Dynamic: description-content-type
Dynamic: home-page
Dynamic: license
Dynamic: requires-python
Dynamic: summary
